[
    {
        "entryId": "LYsfmuNBkyfXIyD2yKViC",
        "path": [
            0,
            0
        ],
        "value": "Wer sind wir?"
    },
    {
        "entryId": "LYsfmuNBkyfXIyD2yKViC",
        "path": [
            1,
            0
        ],
        "value": "DreamPip"
    },
    {
        "entryId": "LYsfmuNBkyfXIyD2yKViC",
        "path": [
            1,
            1
        ],
        "value": "ist Fintech für Mitgefühl."
    },
    {
        "entryId": "LYsfmuNBkyfXIyD2yKViC",
        "path": [
            2,
            0
        ],
        "value": "Wir plexen die Erfahrung des Investierens und Crowdfundings, verbinden Gemeinschaften auf der ganzen Welt, in finanziellen Aufträgen, die darauf abzielen, nichts als Glück zu erfüllen, durch gesunden Wettbewerb.\n\nUnsere organisatorische Struktur ist autorial und benannt "
    },
    {
        "entryId": "LYsfmuNBkyfXIyD2yKViC",
        "path": [
            2,
            1,
            0
        ],
        "value": "Nexus Baum"
    },
    {
        "entryId": "LYsfmuNBkyfXIyD2yKViC",
        "path": [
            2,
            2
        ],
        "value": "."
    },
    {
        "entryId": "LYsfmuNBkyfXIyD2yKViC",
        "path": [
            3,
            0
        ],
        "value": "Wir haben unsere ersten Domains im Jahr 2012 gegründet und folgende Struktur entwickelt:"
    },
    {
        "entryId": "LYsfmuNBkyfXIyD2yKViC",
        "path": [
            4,
            0
        ],
        "value": ""
    },
    {
        "entryId": "LYsfmuNBkyfXIyD2yKViC",
        "path": [
            5,
            0
        ],
        "value": "Vorstand (1)"
    },
    {
        "entryId": "LYsfmuNBkyfXIyD2yKViC",
        "path": [
            6,
            0
        ],
        "value": "Strategische und prüfende Entscheidungsfindung."
    },
    {
        "entryId": "LYsfmuNBkyfXIyD2yKViC",
        "path": [
            7,
            0
        ],
        "value": "Nexus Domain (1)"
    },
    {
        "entryId": "LYsfmuNBkyfXIyD2yKViC",
        "path": [
            8,
            0
        ],
        "value": "Nexus Direktoren (0)"
    },
    {
        "entryId": "LYsfmuNBkyfXIyD2yKViC",
        "path": [
            9,
            0
        ],
        "value": "Nexus Leads (1)"
    },
    {
        "entryId": "LYsfmuNBkyfXIyD2yKViC",
        "path": [
            11,
            0
        ],
        "value": "Angelo Reale"
    },
    {
        "entryId": "LYsfmuNBkyfXIyD2yKViC",
        "path": [
            12,
            0
        ],
        "value": "Nexus Doers (0)"
    },
    {
        "entryId": "LYsfmuNBkyfXIyD2yKViC",
        "path": [
            13,
            0
        ],
        "value": ""
    },
    {
        "entryId": "LYsfmuNBkyfXIyD2yKViC",
        "path": [
            14,
            0
        ],
        "value": ""
    },
    {
        "entryId": "LYsfmuNBkyfXIyD2yKViC",
        "path": [
            15,
            0
        ],
        "value": "Menschen (0)"
    },
    {
        "entryId": "LYsfmuNBkyfXIyD2yKViC",
        "path": [
            16,
            0
        ],
        "value": "Admin-Domäne (0)"
    },
    {
        "entryId": "LYsfmuNBkyfXIyD2yKViC",
        "path": [
            17,
            0
        ],
        "value": "(Vorteile, Karriereentwicklung, psychische Gesundheit)"
    },
    {
        "entryId": "LYsfmuNBkyfXIyD2yKViC",
        "path": [
            18,
            0
        ],
        "value": ""
    },
    {
        "entryId": "LYsfmuNBkyfXIyD2yKViC",
        "path": [
            19,
            0
        ],
        "value": ""
    },
    {
        "entryId": "LYsfmuNBkyfXIyD2yKViC",
        "path": [
            20,
            0
        ],
        "value": "Finanzen (0)"
    },
    {
        "entryId": "LYsfmuNBkyfXIyD2yKViC",
        "path": [
            21,
            0
        ],
        "value": "FinOps Domäne (0)"
    },
    {
        "entryId": "LYsfmuNBkyfXIyD2yKViC",
        "path": [
            22,
            0
        ],
        "value": "(Buchhaltung, Budgetierung und Beschaffung)"
    },
    {
        "entryId": "LYsfmuNBkyfXIyD2yKViC",
        "path": [
            23,
            0
        ],
        "value": ""
    },
    {
        "entryId": "LYsfmuNBkyfXIyD2yKViC",
        "path": [
            24,
            0
        ],
        "value": ""
    },
    {
        "entryId": "LYsfmuNBkyfXIyD2yKViC",
        "path": [
            25,
            0
        ],
        "value": "CISO (0)"
    },
    {
        "entryId": "LYsfmuNBkyfXIyD2yKViC",
        "path": [
            26,
            0
        ],
        "value": "Regulationsbereich (0)"
    },
    {
        "entryId": "LYsfmuNBkyfXIyD2yKViC",
        "path": [
            27,
            0
        ],
        "value": "(Gesetz, Compliance und Kündigungen)"
    },
    {
        "entryId": "LYsfmuNBkyfXIyD2yKViC",
        "path": [
            28,
            0
        ],
        "value": ""
    },
    {
        "entryId": "LYsfmuNBkyfXIyD2yKViC",
        "path": [
            29,
            0
        ],
        "value": ""
    },
    {
        "entryId": "LYsfmuNBkyfXIyD2yKViC",
        "path": [
            30,
            0
        ],
        "value": "Operationen (0)"
    },
    {
        "entryId": "LYsfmuNBkyfXIyD2yKViC",
        "path": [
            31,
            0
        ],
        "value": "GenOps-Domain (0)"
    },
    {
        "entryId": "LYsfmuNBkyfXIyD2yKViC",
        "path": [
            32,
            0
        ],
        "value": "(Mitarbeiter, interne Kommunikation, Büros)"
    },
    {
        "entryId": "LYsfmuNBkyfXIyD2yKViC",
        "path": [
            33,
            0
        ],
        "value": ""
    },
    {
        "entryId": "LYsfmuNBkyfXIyD2yKViC",
        "path": [
            34,
            0
        ],
        "value": ""
    },
    {
        "entryId": "LYsfmuNBkyfXIyD2yKViC",
        "path": [
            35,
            0
        ],
        "value": "Umsatz (0)"
    },
    {
        "entryId": "LYsfmuNBkyfXIyD2yKViC",
        "path": [
            36,
            0
        ],
        "value": "BizDev Domain (0)"
    },
    {
        "entryId": "LYsfmuNBkyfXIyD2yKViC",
        "path": [
            37,
            0
        ],
        "value": "(Verkauf, Partnerschaften, Kundenbeziehungen)"
    },
    {
        "entryId": "LYsfmuNBkyfXIyD2yKViC",
        "path": [
            38,
            0
        ],
        "value": ""
    },
    {
        "entryId": "LYsfmuNBkyfXIyD2yKViC",
        "path": [
            39,
            0
        ],
        "value": ""
    },
    {
        "entryId": "LYsfmuNBkyfXIyD2yKViC",
        "path": [
            40,
            0
        ],
        "value": "Technologie (0)"
    },
    {
        "entryId": "LYsfmuNBkyfXIyD2yKViC",
        "path": [
            41,
            0
        ],
        "value": "DevSecOps Domain (0)"
    },
    {
        "entryId": "LYsfmuNBkyfXIyD2yKViC",
        "path": [
            42,
            0
        ],
        "value": "(Infrastruktur, Sicherheit, Cloud-Ressourcen)"
    },
    {
        "entryId": "LYsfmuNBkyfXIyD2yKViC",
        "path": [
            43,
            0
        ],
        "value": "Sophos-Domäne (0)"
    },
    {
        "entryId": "LYsfmuNBkyfXIyD2yKViC",
        "path": [
            44,
            0
        ],
        "value": "(Forschung & Entwicklung)"
    },
    {
        "entryId": "LYsfmuNBkyfXIyD2yKViC",
        "path": [
            45,
            0
        ],
        "value": ""
    },
    {
        "entryId": "LYsfmuNBkyfXIyD2yKViC",
        "path": [
            46,
            0
        ],
        "value": ""
    },
    {
        "entryId": "LYsfmuNBkyfXIyD2yKViC",
        "path": [
            47,
            0
        ],
        "value": "Produkt (0)"
    },
    {
        "entryId": "LYsfmuNBkyfXIyD2yKViC",
        "path": [
            48,
            0
        ],
        "value": "FinCore-Domäne (0)"
    },
    {
        "entryId": "LYsfmuNBkyfXIyD2yKViC",
        "path": [
            49,
            0
        ],
        "value": "Unsere Finanzplattform, die Open-Source ist, obwohl proprietär, hier gefunden."
    },
    {
        "entryId": "LYsfmuNBkyfXIyD2yKViC",
        "path": [
            50,
            0
        ],
        "value": "CommProd Domain (0)"
    },
    {
        "entryId": "LYsfmuNBkyfXIyD2yKViC",
        "path": [
            51,
            0
        ],
        "value": "Unsere öffentlich zugängliche Reihe von FinProd-Funktionen."
    },
    {
        "entryId": "LYsfmuNBkyfXIyD2yKViC",
        "path": [
            52,
            0
        ],
        "value": "GovProd-Domäne (0)"
    },
    {
        "entryId": "LYsfmuNBkyfXIyD2yKViC",
        "path": [
            53,
            0
        ],
        "value": "Unser Gov Cloud-Set von Regierungsfunktionen."
    },
    {
        "entryId": "LYsfmuNBkyfXIyD2yKViC",
        "path": [
            54,
            0
        ],
        "value": "EnterProd-Domäne (0)"
    },
    {
        "entryId": "LYsfmuNBkyfXIyD2yKViC",
        "path": [
            55,
            0
        ],
        "value": "Unser Unternehmenssatz von Funktionen."
    },
    {
        "entryId": "LYsfmuNBkyfXIyD2yKViC",
        "path": [
            56,
            0
        ],
        "value": ""
    },
    {
        "entryId": "LYsfmuNBkyfXIyD2yKViC",
        "path": [
            57,
            0
        ],
        "value": ""
    },
    {
        "entryId": "LYsfmuNBkyfXIyD2yKViC",
        "path": [
            58,
            0
        ],
        "value": "Marketing (0)"
    },
    {
        "entryId": "LYsfmuNBkyfXIyD2yKViC",
        "path": [
            59,
            0
        ],
        "value": "Präsenzbereich (0)"
    },
    {
        "entryId": "LYsfmuNBkyfXIyD2yKViC",
        "path": [
            60,
            0
        ],
        "value": "(Markenbildung, Soziale Medien, Gemeinschaftsbeziehungen)"
    },
    {
        "entryId": "LYsfmuNBkyfXIyD2yKViC",
        "path": [
            61,
            0
        ],
        "value": "Intelligence Domain (0)"
    },
    {
        "entryId": "LYsfmuNBkyfXIyD2yKViC",
        "path": [
            62,
            0
        ],
        "value": "(Analytics, Business Intelligence, AI Vorhersagen)"
    },
    {
        "entryId": "LYsfmuNBkyfXIyD2yKViC",
        "path": [
            63,
            0
        ],
        "value": "\n\n\n"
    }
]